sls_sdk/VERSION
sls_sdk/__init__.py
sls_sdk/base.py
sls_sdk/exceptions.py
sls_sdk/py.typed
sls_sdk/lib/__init__.py
sls_sdk/lib/captured_event.py
sls_sdk/lib/emitter.py
sls_sdk/lib/error.py
sls_sdk/lib/error_captured_event.py
sls_sdk/lib/id.py
sls_sdk/lib/imports.py
sls_sdk/lib/name.py
sls_sdk/lib/notice.py
sls_sdk/lib/stack_trace_string.py
sls_sdk/lib/tag_value.py
sls_sdk/lib/tags.py
sls_sdk/lib/timing.py
sls_sdk/lib/trace.py
sls_sdk/lib/warning.py
sls_sdk/lib/warning_captured_event.py
sls_sdk/lib/instrumentation/__init__.py
sls_sdk/lib/instrumentation/flask.py
sls_sdk/lib/instrumentation/http.py
sls_sdk/lib/instrumentation/import_hook.py
sls_sdk/lib/instrumentation/logging.py
sls_sdk/lib/instrumentation/wrapper.py
serverless_sdk-0.6.0.dist-info/METADATA
serverless_sdk-0.6.0.dist-info/WHEEL
serverless_sdk-0.6.0.dist-info/top_level.txt
serverless_sdk-0.6.0.dist-info/RECORD
