Metadata-Version: 2.1
Name: serverless-sdk
Version: 0.6.0
Summary: Serverless SDK for Python
Author: serverlessinc
Project-URL: changelog, https://github.com/serverless/console/blob/main/python/packages/sdk/CHANGELOG.md
Project-URL: documentation, https://github.com/serverless/console/tree/main/python/packages/sdk
Project-URL: homepage, https://www.serverless.com/console
Project-URL: repository, https://github.com/serverless/console
Classifier: Programming Language :: Python :: 3 :: Only
Classifier: Programming Language :: Python :: 3.7
Classifier: Programming Language :: Python :: 3.8
Classifier: Programming Language :: Python :: 3.9
Classifier: Programming Language :: Python :: 3.10
Classifier: Programming Language :: Python :: 3.11
Requires-Python: >=3.7
Requires-Dist: backports.cached-property
Requires-Dist: blinker >=1.5
Requires-Dist: js-regex <1.1.0,>=1.0.1
Requires-Dist: typing-extensions >=4.4
Provides-Extra: tests
Requires-Dist: aiohttp >=3.8.4 ; extra == 'tests'
Requires-Dist: black >=22.12 ; extra == 'tests'
Requires-Dist: flask >=2.2.3 ; extra == 'tests'
Requires-Dist: importlib-metadata >=5.2 ; extra == 'tests'
Requires-Dist: mypy >=1.2 ; extra == 'tests'
Requires-Dist: pytest >=7.2 ; extra == 'tests'
Requires-Dist: pytest-httpserver >=1.0.6 ; extra == 'tests'
Requires-Dist: requests >=2.28.2 ; extra == 'tests'
Requires-Dist: ruff >=0.0.199 ; extra == 'tests'
Requires-Dist: urllib3 >=1.26.15 ; extra == 'tests'
Requires-Dist: yarl ~=1.8.0 ; extra == 'tests'
